significant_figures/__init__.py
significant_figures/functions.py
significant_figures-0.0.4.dist-info/METADATA
significant_figures-0.0.4.dist-info/WHEEL
significant_figures-0.0.4.dist-info/top_level.txt
significant_figures-0.0.4.dist-info/RECORD
