Metadata-Version: 2.1
Name: significant-figures
Version: 0.0.4
Summary: Library for rounding a number to a quantity of significant figures
Home-page: https://github.com/luisgn98
Author: Luis García Nnomo
Author-email: luisnnomo@hotmail.com
License: MIT
